jupyspace/__init__.py
jupyspace-0.0.4.dist-info/METADATA
jupyspace-0.0.4.dist-info/WHEEL
jupyspace-0.0.4.dist-info/licenses/LICENSE.txt
jupyspace-0.0.4.dist-info/RECORD
