Metadata-Version: 2.1
Name: jupyspace
Version: 0.0.4
Project-URL: Documentation, https://github.com/davidbrochart/jupyspace#readme
Project-URL: Issues, https://github.com/davidbrochart/jupyspace/issues
Project-URL: Source, https://github.com/davidbrochart/jupyspace
Author-email: David Brochart <david.brochart@gmail.com>
License: MIT
License-File: LICENSE.txt
Keywords: conda,jupyter
Classifier: Development Status :: 4 - Beta
Classifier: Programming Language :: Python
Classifier: Programming Language :: Python :: 3.8
Classifier: Programming Language :: Python :: 3.9
Classifier: Programming Language :: Python :: 3.10
Classifier: Programming Language :: Python :: 3.11
Classifier: Programming Language :: Python :: Implementation :: CPython
Classifier: Programming Language :: Python :: Implementation :: PyPy
Requires-Python: >=3.8
Requires-Dist: fps-localspace
Requires-Dist: fps-spacex
Requires-Dist: jupyspace-api
Provides-Extra: test
Requires-Dist: httpx; extra == 'test'
Requires-Dist: pytest; extra == 'test'
Requires-Dist: pytest-asyncio; extra == 'test'
